{"0": {"file_path": "hr.jhist_department_ix.md", "full_doc_id": "doc-580cfebdd0187e83c6cb75c4aee86c31", "content": "# Documentation: `JHIST_DEPARTMENT_IX` (Index)\n\n---\n\n## Object Overview\n\n**Type:** Index  \n**Name:** `JHIST_DEPARTMENT_IX`  \n**Schema:** `HR`  \n**Table Indexed:** `HR.JOB_HISTORY`  \n**Primary Purpose:**  \nThe `JHIST_DEPARTMENT_IX` index is designed to optimize query performance for operations involving the `DEPARTMENT_ID` column in the `JOB_HISTORY` table. By providing efficient access paths for queries filtering or joining on `DEPARTMENT_ID`, this index supports faster data retrieval and improved overall performance for department-based lookups in job history records.\n\n**Business Context & Use Cases:**  \n- Frequently used in HR analytics and reporting to retrieve job history records by department.\n- Supports business processes such as employee movement tracking, departmental audits, and compliance reporting.\n- Enhances performance for applications and reports that analyze employee job transitions within specific departments.\n\n---\n\n## Detailed Structure & Components\n\n- **Index Name:** `JHIST_DEPARTMENT_IX`\n- **Table Indexed:** `HR.JOB_HISTORY`\n- **Indexed Column(s):**\n  - `DEPARTMENT_ID` (Ascending order)\n- **Index Type:** Standard B-tree (default for Oracle unless otherwise specified)\n- **Logging:** `NOLOGGING` (index creation and maintenance operations are not logged in the redo log)\n- **Compression:** `NOCOMPRESS` (index entries are not compressed)\n- **Parallelism:** `NOPARALLEL` (index operations are performed serially)\n\n---\n\n## Component Analysis\n\n### Indexed Columns\n\n| Column Name     | Order     | Data Type | Notes |\n|-----------------|-----------|-----------|-------|\n| `DEPARTMENT_ID` | Ascending | (As defined in `JOB_HISTORY`) | Primary key for department-based queries |\n\n- **Business Meaning:**  \n  `DEPARTMENT_ID` identifies the department associated with each job history record. Indexing this column accelerates queries that filter or join on department, which is common in HR reporting and analytics.\n\n- **Data Type:**  \n  The data type is inherited from the `JOB_HISTORY` table definition (commonly `NUMBER` or similar in HR schemas).\n\n- **Order:**  \n  Ascending (`ASC`) order is specified, which is the default and optimal for range scans and equality searches.\n\n### Index Properties\n\n- **NOLOGGING:**  \n  - **Significance:** Reduces redo log generation during index creation and maintenance, which can speed up bulk operations.\n  - **Business Rationale:** Useful for large data loads or rebuilds where recovery from media failure is not a primary concern during the operation.\n  - **Caveat:** Increases risk of data loss for the index in the event of a failure during creation or rebuild.\n\n- **NOCOMPRESS:**  \n  - **Significance:** Index entries are stored uncompressed.\n  - **Business Rationale:** May be chosen to avoid the CPU overhead of compression, especially if the indexed column has high cardinality or low repetition.\n\n- **NOPARALLEL:**  \n  - **Significance:** Index creation and maintenance are performed serially.\n  - **Business Rationale:** Ensures predictable resource usage and avoids contention in environments where parallel DML is not required or could impact other workloads.\n\n---\n\n## Complete Relationship Mapping\n\n- **Table Dependency:**  \n  - The index is dependent on the `HR.JOB_HISTORY` table and specifically on the `DEPARTMENT_ID` column.\n- **Downstream Dependencies:**  \n  - No objects directly depend on this index, but queries, views, and procedures that access `JOB_HISTORY` by `DEPARTMENT_ID` will benefit from its presence.\n- **Impact of Changes:**  \n  - Dropping or altering the index may degrade performance for department-based queries.\n  - Changes to the `DEPARTMENT_ID` column (data type, name, or removal) will invalidate the index.\n\n---\n\n## Comprehensive Constraints & Rules\n\n- **Constraints Enforced:**  \n  - The index itself does not enforce constraints but supports the efficient enforcement of foreign key or check constraints involving `DEPARTMENT_ID`.\n- **Business Rules Supported:**  \n  - Accelerates business rules and processes that require rapid access to job history by department.\n- **Security & Access:**  \n  - No direct security implications; access is governed by table-level privileges.\n- **Data Integrity:**  \n  - The index does not enforce data integrity but supports efficient query access.\n\n- **Performance Implications:**  \n  - Improves performance for queries filtering or joining on `DEPARTMENT_ID`.\n  - May slightly impact DML performance (INSERT/UPDATE/DELETE) due to index maintenance overhead.\n\n---\n\n## Usage Patterns & Integration\n\n- **Common Query Patterns:**\n  - `SELECT * FROM HR.JOB_HISTORY WHERE DEPARTMENT_ID = :dept_id`\n  - Joins between `JOB_HISTORY` and `DEPARTMENTS` on `DEPARTMENT_ID`\n  - Aggregations and analytics grouped by department\n\n- **Integration Points:**\n  - HR reporting tools and dashboards\n  - Application modules tracking employee movement by department\n  - Data warehouse ETL processes\n\n- **Performance Characteristics:**\n  - Optimizes equality and range queries on `DEPARTMENT_ID`\n  - Not used for queries that do not reference `DEPARTMENT_ID`\n\n- **Tuning Considerations:**\n  - Monitor index usage and maintenance costs\n  - Consider compressing or parallelizing if workload or data volume changes\n\n---\n\n## Implementation Details\n\n- **Storage Specifications:**\n  - Inherits tablespace and storage parameters from the default or specified settings for the `HR` schema.\n  - `NOLOGGING` reduces redo log usage during index operations.\n\n- **Special Database Features:**\n  - None explicitly used beyond standard index options.\n\n- **Maintenance & Operations:**\n  - Rebuild index periodically if fragmentation occurs.\n  -", "__id__": "chunk-d7148cba77459ba894ec6242be8ebebc", "__created_at__": 1754139616, "__vector__": [-0.011384943500161171, 0.053342681378126144, 0.07857664674520493, 0.02343153767287731, 0.0520193837583065, 0.01844634674489498, 0.006205820944160223, -0.004411951173096895, -0.012411641888320446, 0.02032862789928913, 0.04168395325541496, 0.0033510292414575815, 0.01074040587991476, -0.0131759624928236, 0.054757244884967804, 0.03246648237109184, 0.00011461233225418255, 0.013666495680809021, 0.014966980554163456, 0.015548775903880596, 0.024891730397939682, 0.007243927102535963, -0.009553998708724976, -0.0015443253796547651, 0.0037731165066361427, 0.024754837155342102, -0.03985871002078056, -0.004044050816446543, 0.03383541479706764, -0.06538927555084229, 0.03511308506131172, -0.020739305764436722, -0.0066621312871575356, 0.03390385955572128, 0.03919706121087074, -0.008333368226885796, 0.030413087457418442, 0.01919925957918167, 0.0029802771750837564, 0.015149504877626896, 0.0329684242606163, -0.02393347956240177, 0.0061430782079696655, 0.030207747593522072, -0.05169996619224548, 0.027720855548977852, 0.0011008487781509757, -0.02091042324900627, 0.02230216935276985, -0.006046112626791, -0.03465677425265312, 0.02628347836434841, -0.027789302170276642, -0.00825921818614006, -0.003425179747864604, 0.013712126761674881, -0.028587844222784042, 0.03360725939273834, 0.027766486629843712, -0.04777569696307182, 0.04006405174732208, -0.04656647518277168, -0.03310531750321388, 0.002288681687787175, -0.003530701622366905, 0.049464043229818344, 0.01800144463777542, 0.0406116247177124, -0.0007757276180200279, -0.024891730397939682, 0.056080546230077744, 0.0335388109087944, -0.020784936845302582, 0.004908188711851835, 0.021982751786708832, 0.0031485415529459715, -0.006086039822548628, 0.011852662079036236, -0.0213895495980978, -0.01051225047558546, -0.04451307654380798, 0.025484934449195862, 0.008042470552027225, -0.01014720182865858, -0.0176820270717144, -0.03520434722304344, -0.01732838712632656, -0.01947304606437683, -0.054164040833711624, 0.0019863760098814964, -0.02610095404088497, 0.012982030399143696, -0.02142377197742462, 0.010472322814166546, -0.03623104467988014, -0.03267182409763336, 0.0007479212363250554, -0.00045809283619746566, -0.0321698822081089, 0.0368470624089241, 0.004856853745877743, -0.00917754229158163, 0.007135553285479546, -0.009394289925694466, 0.029272310435771942, 0.03143978491425514, -0.061693161725997925, -0.00466862553730607, 0.02194852940738201, -0.013461155816912651, -0.07926110923290253, -0.02393347956240177, 0.0010423840722069144, 0.02614658512175083, -0.01026698388159275, -0.04569948464632034, -0.01911940425634384, 0.0312572605907917, -0.03723492845892906, -0.04145579785108566, -0.043463561683893204, -0.027469884604215622, -0.02000921033322811, -0.007551936898380518, -0.010426691733300686, -0.02314634434878826, 0.029317941516637802, -0.013598049059510231, -0.04823200777173042, -0.0402693897485733, 0.04093104228377342, -0.007666014134883881, -0.0018566128564998507, -0.0401553139090538, -0.027903379872441292, -0.0007315225666388869, -0.03607133403420448, 0.04109074920415878, -0.03253493085503578, -0.049235887825489044, 0.02135532535612583, -0.004363467916846275, 0.0625145211815834, 0.01150472555309534, -0.0169975608587265, 0.01026127953082323, 0.02010047249495983, 0.02616940066218376, 0.060917433351278305, 0.051289286464452744, 0.00863567367196083, -0.01905095763504505, -0.0326261930167675, -0.04330385476350784, 0.02379658631980419, -0.02381940186023712, 0.027583962306380272, -0.010563584975898266, 0.009006425738334656, -0.02294100448489189, -0.004346356261521578, 0.015149504877626896, 0.02436697483062744, -0.015081058256328106, 4.300190630601719e-05, -0.0022116792388260365, -0.04508346691727638, 0.003696114057675004, -0.07606694102287292, 0.011042711324989796, 0.01127657014876604, -0.08350479602813721, -0.0035221457947045565, 0.02051115222275257, 0.0485970564186573, 0.058818407356739044, -0.007723052985966206, -0.03527279198169708, -0.0033852525521069765, -0.03677861765027046, -0.01959853060543537, -0.022724255919456482, -0.060552388429641724, 0.059639766812324524, -0.030002407729625702, -0.02582716755568981, -0.0657086968421936, 0.03201017156243324, -0.00710703432559967, 0.062468890100717545, 0.02303226664662361, 0.0326261930167675, 0.02103590779006481, 0.01804707571864128, -0.011202420108020306, 0.00649671908468008, 0.0034109200350940228, -0.015081058256328106, -0.00847596488893032, -0.000630991708021611, 0.0338810458779335, -0.00933725107461214, 0.041524242609739304, 0.03780531510710716, -0.03908298537135124, 0.04394268989562988, -0.02397911064326763, 0.029842698946595192, -0.02386503294110298, -0.04695433750748634, 0.01684926077723503, -0.03933395445346832, 0.0282912440598011, 0.031165998429059982, 0.03196454048156738, -0.0406116247177124, -0.049692198634147644, -0.00205339677631855, -0.015389067120850086, -0.025165516883134842, -0.03157667815685272, 0.002445538528263569, 0.0033852525521069765, -0.006051816511899233, 0.023157751187682152, 0.03349317982792854, -0.0013361338060349226, -0.0446043387055397, 0.01630168780684471, -0.01957571506500244, 0.021891489624977112, -0.030048038810491562, -0.02307789772748947, -0.007055699359625578, -0.029181048274040222, -0.0205339677631855, -0.03769123554229736, 0.01170436106622219, 0.029226679354906082, 0.04236841946840286, -0.03390385955572128, 0.03406357020139694, -0.029705805703997612, -0.005837921053171158, -0.0007297401316463947, -0.004406247287988663, -0.014716009609401226, -0.079854317009449, 0.050604820251464844, 0.00575236277654767, -0.029044155031442642, -0.026648525148630142, -0.01828663796186447, -0.02345435321331024, -0.049555305391550064, -0.025599012151360512, -0.04234560206532478, 0.050285402685403824, 0.0030886507593095303, 0.012537127360701561, 0.012594166211783886, -0.01688348315656185, 0.006365529727190733, -0.0061887092888355255, -0.027561146765947342, 0.04433055222034454, 0.0691310241818428, -0.058453358709812164, -0.03363007307052612, -0.013598049059510231, 0.030800949782133102, 0.031120367348194122, 0.012776690535247326, -0.010654847137629986, -0.004748479928821325, -0.0006912389071658254, -0.013518194667994976, 0.01590241678059101, -0.020899014547467232, -0.057449474930763245, 0.00855011586099863, 0.02409318834543228, 0.006194413173943758, 0.007991135120391846, 0.024982992559671402, 0.02046552114188671, 0.004212315194308758, 0.012856544926762581, -0.002985981060191989, -0.012571350671350956, -0.04503783583641052, 0.008738343603909016, 0.015560183674097061, -0.013233001343905926, -0.014065767638385296, 0.03759997338056564, 0.02245047129690647, -0.026602894067764282, 0.01139064785093069, -0.05288637429475784, 0.03406357020139694, 0.02215386927127838, 0.04759317263960838, -0.02132110297679901, 0.012320379726588726, 0.03278589993715286, -0.0024540943559259176, -0.049920354038476944, -0.028998523950576782, -0.00951407104730606, 0.0005062193376943469, 0.001542899408377707, 0.02046552114188671, 0.0027521220035851, -0.02194852940738201, -0.01953008398413658, 0.02199416048824787, -0.0004103228566236794, -0.007563344668596983, 0.00017726588703226298, -0.014134214259684086, -0.013461155816912651, 0.01998639479279518, -0.02266721799969673, 0.010974264703691006, -0.02646600268781185, -0.014385184273123741, -0.00019874455756507814, 0.00428361352533102, 0.01026698388159275, 0.015046834945678711, -0.014944165013730526, -0.04113638028502464, 0.03269463777542114, 0.0007728756754659116, -0.00117286026943475, -0.01673518307507038, 0.003011648543179035, 0.004956671502441168, 0.014544893056154251, -0.0012805210426449776, -0.015206543728709221, -0.03493056073784828, -0.014761640690267086, -0.060050446540117264, 0.01032972615212202, -0.02824561297893524, 0.030048038810491562, 0.006097447592765093, -0.01690629869699478, -0.05169996619224548, 0.004132460802793503, 0.002004913752898574, -0.009303027763962746, -0.012776690535247326, -0.027903379872441292, -0.00435206014662981, -0.07227956503629684, -0.0666213184595108, 0.010632031597197056, -0.03486211225390434, -0.03837570175528526, 0.033995121717453, -0.02045411244034767, 0.0529320053756237, -0.01197814755141735, -0.00788846518844366, 0.03472521901130676, 0.020830567926168442, 0.014636155217885971, 0.03874075040221214, 0.004300725180655718, 0.002240198664367199, -0.030276194214820862, -0.02815435081720352, 0.01752231828868389, -0.009930454194545746, 0.022051198408007622, 0.02397911064326763, 0.04524317383766174, 0.027332991361618042, 0.010227056220173836, -0.002086193999275565, -0.00151152815669775, 0.03367570415139198, 0.025713089853525162, -0.01627887226641178, 0.01567426137626171, -0.03645920008420944, -0.03372133523225784, -0.010569289326667786, 0.002646600129082799, -0.02312352880835533, -0.0010174295166507363, -0.04058880731463432, 0.02044270560145378, -0.012856544926762581, 0.01128227449953556, 0.06447665393352509, 0.011898293159902096, -0.0022016975563019514, -0.03858104348182678, 0.02370532415807247, -0.03271745517849922, -0.005441501270979643, -0.046087346971035004, 0.0231007132679224, 0.046589288860559464, -0.0007158368825912476, -0.00845885369926691, 0.014601931907236576, 0.025279594585299492, 0.007814315147697926, 0.00613737478852272, 0.00590921938419342, -0.058407727628946304, -0.04307569935917854, 0.059046562761068344, 0.004337800666689873, 0.005966258235275745, -0.025553381070494652, -0.028930077329277992, 0.0322839580476284, -0.049829091876745224, -0.07442422211170197, 0.007078514900058508, 0.01707741618156433, -0.01747668720781803, 0.01824100688099861, -0.01909658871591091, -0.0057723261415958405, 0.04485531151294708, 0.02124124765396118, 0.03826162591576576, -0.06721451878547668, 0.0031029104720801115, 0.050787344574928284, -0.0022145311813801527, 0.055898021906614304, 0.0012484366307035089, -0.0031171701848506927, -0.0011471927864477038, 0.02028299681842327, 0.0009710855083540082, -0.0061887092888355255, 0.028724737465381622, 0.004888224881142378, -0.01995217055082321, -0.004905336536467075, 0.02438979037106037, 0.01013009063899517, 0.057677630335092545, 0.03782812878489494, -0.025416487827897072, 0.0198495015501976, -0.004132460802793503, 0.01654125191271305, -0.0005322432843968272, 0.012731059454381466, 0.00405831029638648, 0.011424871161580086, 0.0009076298447325826, 0.00942851323634386, 0.060278601944446564, -0.0110940458253026, -0.013369893655180931, -0.03276308625936508, -0.005857884418219328, 0.0031257260125130415, -0.0394708476960659, 0.00854441151022911, -0.01788736693561077, 0.05197375267744064, -0.021663334220647812, 0.027880564332008362, 0.030983474105596542, -0.0515630729496479, 0.009822080843150616, 0.02824561297893524, -0.03340191766619682, 0.065252386033535, -0.03791939094662666, -0.01654125191271305, -0.008983610197901726, 0.033995121717453, 0.04307569935917854, 0.057038795202970505, 0.01989513263106346, 0.025142701342701912, 0.03600288927555084, -0.02127547189593315, -0.009553998708724976, 0.07273587584495544, -0.00916043110191822, -0.010728998109698296, 0.01987231709063053, -0.0384441502392292, -0.0377596840262413, 0.059913553297519684, 0.0015699928626418114, -0.009502663277089596, 0.01052936166524887, 0.002244476694613695, 0.015594406984746456, 0.006793320644646883, 0.008937979117035866, -0.02637474052608013, -0.00462299445644021, -0.010632031597197056, -0.00855011586099863, -0.004565955605357885, 0.049327149987220764, 0.009240285493433475, 0.026716971769928932, -0.01109975017607212, -0.02381940186023712, -0.0075804563239216805, 0.01802426017820835, -0.007859946228563786, -0.0217888206243515, -0.006040408741682768, -0.01062062382698059, -0.01096285693347454, 0.0110084880143404, 0.001207083580084145, 0.01724853180348873, -0.04556259140372276, -0.09591644257307053, 0.02234780043363571, 0.003895749803632498, -0.004956671502441168, -0.0026865273248404264, 0.025074254721403122, 0.060050446540117264, -0.0063370103016495705, 0.014887126162648201, 0.01655265875160694, 0.010341133922338486, -0.0032312478870153427, 0.01738542504608631, -0.00880108680576086, 0.005857884418219328, 0.010392468422651291, 0.030230563133955002, 0.022792702540755272, -0.0030030927155166864, 0.010426691733300686, 0.03561502322554588, 0.028519397601485252, 0.04079414904117584, -0.03960774093866348, -0.0180812980979681, 0.04013249650597572, 0.03178201615810394, -0.03394949063658714, 0.006793320644646883, -0.02011187933385372, 0.003995567560195923, -0.0110940458253026, -0.010500842705368996, 0.006160189863294363, -0.015400474891066551, -0.030367456376552582, 0.028587844222784042, -0.02363687753677368, -0.03497619181871414, 0.02101309224963188, -0.061921317130327225, -0.030184932053089142, 0.013734942302107811, 0.04877958074212074, -0.02443542145192623, -0.01141346339136362, -0.02176600508391857, 0.0467718131840229, 0.005766622256487608, -0.02598687633872032, -0.02445823699235916, 0.05694753676652908, 0.0381019152700901, -0.011966739781200886, -0.01812692917883396, 0.01746528036892414, 0.03447424992918968, -0.021708965301513672, -0.00832196045666933, 0.03883201256394386, 0.029181048274040222, -0.0203058123588562, -0.0005907080485485494, -0.00034116330789402127, 0.01824100688099861, 0.014362368732690811, -0.008424630388617516, 0.0019407450454309583, -0.01114538125693798, 0.027218913659453392, 0.01566285453736782, 0.01148191001266241, 0.013301447033882141, -0.0015257878694683313, -0.01822960004210472, 0.008179363794624805, -0.0018737245118245482, -0.01908518187701702, -0.009799265302717686, 0.03260337561368942, 0.0030487237963825464, 0.0282912440598011, 0.003582036355510354, -0.0425509437918663, -0.014955572783946991, -0.012731059454381466, -0.028679106384515762, -0.028815999627113342, 0.0657086968421936, 0.02219950035214424, -0.012582758441567421, -0.0014295348664745688, -0.02420726604759693, 0.01905095763504505, 0.005903515499085188, -0.054894138127565384, -0.009388585574924946, 0.026534447446465492, -0.000721184303984046, -0.046680551022291183, -0.031051920726895332, 0.009479847736656666, 0.014932757243514061, -0.014373776502907276, -0.04054317623376846, 0.008920867927372456, -0.02580435201525688, 0.02359124645590782, -0.00843033380806446, -0.0016498472541570663, -0.01764780469238758, 0.060004815459251404, 0.01900532655417919, 0.009382882155478, 0.0366189070045948, 0.02402474172413349, 0.018138337880373, 0.01793299801647663, -0.007146961055696011, 0.02216527611017227, -0.027469884604215622, -0.04629268869757652, -0.01738542504608631, -0.0030401679687201977, -0.01306188479065895, 0.04800385236740112, 0.051015499979257584, 0.01894828863441944, -0.0129478070884943, -0.03349317982792854, -0.00588640384376049, -0.003282582852989435, 0.03497619181871414, -0.004049754701554775, 0.027082020416855812, 0.00978785753250122, -0.0063598258420825005, 0.041524242609739304, 0.01927911303937435, 0.00455454783514142, 0.011567467823624611, 0.041843660175800323, 0.0018380752298980951, -0.005159159190952778, 0.0025667459703981876, 0.0643397644162178, -0.00981637742370367, -0.008892348036170006, -0.01181843876838684, -0.01610775664448738, -0.028131535276770592, 0.0005536327953450382, 0.01981527730822563, 0.009303027763962746, -0.027583962306380272, 0.003910009749233723, -0.03908298537135124, 8.609293581685051e-05, -0.053570836782455444, 0.026694156229496002, 0.01809270679950714, 0.029591728001832962, 0.0011742862407118082, 0.059639766812324524, -0.01623324118554592, 0.02294100448489189, -0.01565144583582878, -0.023294644430279732, 0.0037930801045149565, 0.0041923513635993, -0.027332991361618042, -0.01803566701710224, -0.07154946774244308, -0.007021476048976183, 0.0353640541434288, -0.012502904050052166, 0.008829605765640736, -0.0031257260125130415, 0.003987011965364218, -0.01738542504608631, 0.010004605166614056, 0.03248929977416992, -0.01929052174091339, -0.01810411363840103, 0.02233639359474182, -0.03349317982792854, -0.0261237695813179, 0.01419125311076641, -0.008561523631215096, -0.026671340689063072, -0.0129478070884943, 0.005852180533111095, -0.013404116965830326, 0.011476205661892891, -0.006816136185079813, -0.03408638387918472, -0.02150362730026245, 0.026762602850794792, 0.013803388923406601, -0.04444463178515434, -0.004317836835980415, -0.03835288807749748, 0.0034736627712845802, 0.01706600748002529, 0.03130289167165756, 0.00254820822738111, -0.01751091144979, 0.0062571559101343155, 0.012172079645097256, -0.03976744785904884, 0.009143318980932236, -0.02368250861763954, 0.007563344668596983, -0.02174318954348564, -0.027241729199886322, 0.005424389615654945, -0.02101309224963188, -0.04090822488069534, -0.04070288687944412, 0.02363687753677368, 0.0027164726052433252, 0.006228636484593153, 0.03315094858407974, 0.010974264703691006, 0.007072811014950275, -0.012582758441567421, -0.0479125902056694, 0.05243006348609924, -0.001859464799053967, -0.008316257037222385, 0.0054329452104866505, -0.03899172320961952, 0.043782979249954224, -0.01583397015929222, 0.0244126059114933, -0.031234445050358772, 0.0196213461458683, -0.02015751041471958, 0.0061887092888355255, -0.012753874994814396, 0.011607395485043526, -0.030390271916985512, -0.009884823113679886, 0.049418412148952484, 0.0261237695813179, -0.01123093906790018, -0.0019393190741539001, 0.0378737598657608, 0.004480397328734398, 0.029751436784863472, -0.01950726844370365, 0.00828203372657299, -0.02185726724565029, 0.0006267137941904366, -0.020625228062272072, 0.005584098398685455, -0.01672377437353134, -0.0030715391039848328, -0.00816795602440834, -0.00423798244446516, -0.02824561297893524, 0.008533003740012646, -0.0345655120909214, -0.0037503009662032127, -0.0014716009609401226, 0.004500361159443855, 0.01648421213030815, -0.01799003593623638, -0.03363007307052612, 0.0016954782186076045, -0.07054558396339417, 0.00834477599710226, 0.049600936472415924, -0.024868914857506752, 0.011310793459415436, 0.01715726964175701, 0.025484934449195862, 0.02242765575647354, 0.02045411244034767, -0.01982668600976467, -0.02605532296001911, -0.0424368642270565, -0.00978785753250122, -0.023249013349413872, 0.006399753037840128, -0.0057751783169806, -0.01652984321117401, 0.02370532415807247, 0.012012370862066746, -0.013369893655180931, 0.0057495106011629105, -0.006411160808056593, -0.0063712336122989655, -0.04229997098445892, 0.029044155031442642, -0.0203058123588562, -0.00239135161973536, 0.02354561537504196, 0.0361625961959362, -0.02644318714737892, -0.022952411323785782, 0.012377418577671051, -0.057768892496824265, -0.00949695985764265, -0.023203382268548012, 0.01564003899693489, 0.005102120339870453, -0.025370856747031212, 0.02648881822824478, -0.0051962342113256454, -0.01680362969636917, -0.01647280529141426, -0.01222911849617958, 0.02142377197742462, 0.04293880611658096, -0.025393672287464142, 0.0075348252430558205, 0.014430815353989601, -0.04314414784312248, 0.045950453728437424, -0.025051439180970192, 0.022815518081188202, 0.01851479336619377, 0.02630629390478134, 0.006530942395329475, -0.022610178217291832, -0.03369852155447006, -0.025507749989628792, -0.0074321553111076355, 0.003955640364438295, 0.0019564307294785976, 0.010460915043950081, 0.04207181558012962, -0.001319735194556415, 0.007426451425999403, -0.0014038673834875226, -0.03178201615810394, 0.025142701342701912, 0.009303027763962746, 0.0031599493231624365, 0.04896210506558418, 0.01925629749894142, -0.03871793672442436, -0.005016562063246965, 0.00823640264570713, 0.013472563587129116, -0.0366189070045948, -0.03522716090083122, -0.023180566728115082, 0.001599938259460032, 0.06680383533239365, -0.026557262986898422, 0.03693832457065582, 0.027150467038154602, 0.00880108680576086, 0.001701182103715837, -0.00873264018446207, 0.0022102533839643, 0.012776690535247326, -0.0189939197152853, 0.013963097706437111, 0.012149264104664326, 0.006605092901736498, 0.0031827648635953665, 0.01667814515531063, -0.0466577373445034, -0.012639797292649746, 0.01575411483645439, 0.02060241438448429, -0.025165516883134842, 0.02020314149558544, 0.006433976348489523, 0.01592523232102394, 0.008065286092460155, -0.01113967690616846, 0.0224162470549345, 0.01416843757033348, 0.0018238155171275139, -0.014442223124206066, 0.01416843757033348, -0.01940459944307804, 0.05233880132436752, -0.01700896956026554, -0.015571591444313526, -0.029637359082698822, -0.02582716755568981, 0.01094004139304161, 0.03739463537931442, -0.030983474105596542, -0.025599012151360512, -0.013563825748860836, -0.0005158446147106588, -0.012616981752216816, 0.02582716755568981, -0.030413087457418442, -0.01562863029539585, 0.02340872213244438, 0.008538708090782166, -0.0037902281619608402, 0.014841495081782341, 0.024732021614909172, 0.0466577373445034, -0.02361406199634075, 0.01976964622735977, -0.01703178510069847, -0.03566065430641174, 0.02407037280499935, -0.02605532296001911, -0.014750232920050621, -0.029751436784863472, 0.01423688419163227, 0.01963275484740734, -0.02291818894445896, 0.006376937497407198, 0.005689620040357113, 0.03349317982792854, -0.013347078114748001, -0.010278391651809216, -0.044056765735149384, 0.01322159357368946, -0.004979487042874098, 0.0377596840262413, 0.03420046344399452, 0.0028676255606114864, -0.03915143013000488, 0.02026018127799034, -0.02055678330361843, -0.0224162470549345, 0.014453630894422531, 0.014054359868168831, -0.00849878042936325, -0.0013568103313446045, 0.050376664847135544, -0.01744246482849121, 0.04223152622580528, -0.01071188598871231, -0.0014616191620007157, -0.0013568103313446045, 0.00133114296477288, -0.0026979350950568914, 0.03201017156243324, 0.028610659763216972, 0.009776449762284756, 0.05265821889042854, 0.02222231589257717, 0.061875686049461365, 0.009103392250835896, 0.01711163856089115, 0.0226444024592638, 0.012822321616113186, -0.04214026406407356, 0.0062229325994849205, 0.022838333621621132, -0.0029089786112308502, 0.02039707452058792, 0.054985400289297104, 0.0008584338938817382, -0.0082991449162364, 0.012514311820268631, 0.01585678569972515, 0.02377377077937126, 0.04727375507354736, 0.01672377437353134, -0.004468989558517933, -0.0490533672273159, 0.01590241678059101, 0.01932474412024021, -0.03796502202749252, -0.00398986367508769, 0.029181048274040222, -0.0013432636624202132, 0.022929595783352852, -0.01583397015929222, 0.015058242715895176, 0.049965985119342804, 0.012457272969186306, 0.0033082503359764814, -7.410587568301708e-05, 0.015548775903880596, 0.027469884604215622, -0.029089786112308502, 0.005966258235275745, 0.00162417977117002, -0.029135417193174362, -0.02043129689991474, -0.004882520996034145, -0.03130289167165756, -0.02113857865333557, -0.0049367076717317104, -0.0005917774979025126, -0.01197814755141735, -0.024754837155342102, -0.01313033141195774, -0.020716490224003792, 0.00509926863014698, 0.006605092901736498, 0.00703858770430088, 0.01883421093225479, -0.01978105492889881, 0.0065879812464118, -0.03385822847485542, 0.02102450095117092, 0.0030772429890930653, -0.029386388137936592, -0.00649671908468008, 0.02817716635763645, -0.00532171968370676, 0.001149331801570952, -0.021708965301513672, -0.00879538245499134, 0.029363572597503662, -0.008960794657468796, -0.012491496279835701, -0.00572954723611474, -0.026602894067764282, -0.02121843211352825, 0.01076322142034769, 0.041615504771471024, 0.010095867328345776, 0.00503082200884819, -0.006388345267623663, 0.01579974591732025, 0.030184932053089142, -0.02644318714737892, -0.025713089853525162, 0.013780573382973671, 0.014795864000916481, 0.02119561657309532, 0.0026908053550869226, 0.005338831339031458, 0.01664392091333866, 0.012434457428753376, 0.027332991361618042, -0.0068674711510539055, -0.01575411483645439, -0.03864948824048042, -0.02388784848153591, 0.004423358477652073, 0.010957152582705021, 0.020830567926168442, 0.00793409626930952, 0.013096108101308346, 0.00012129656533943489, -0.005926331039518118, -0.03269463777542114, 0.007198296021670103, -0.013643680140376091, 0.05165433511137962, 0.02246187813580036, -0.026922311633825302, 0.0006883869646117091, -0.001418840023688972, 0.01635872758924961, 0.005826513282954693, -0.00548142846673727, -0.0391286164522171, 0.014373776502907276, -0.0474562793970108, 0.026922311633825302, 0.00505363754928112, 0.03242085129022598, -0.020020617172122, 0.01797862909734249, 0.005880699958652258, 0.01021564844995737, -0.03515871614217758, -0.012685428373515606, 0.01625605672597885, 0.015252173878252506, -0.00037253464688546956, -0.013974505476653576, 0.0006071067182347178, 0.013552417978644371, 0.004483249504119158, 0.028633475303649902, 0.01582256145775318, 0.0014858606737107038, -0.04366890341043472, -0.022792702540755272, 0.025279594585299492, 0.00505363754928112, 0.02280411124229431, -0.022610178217291832, 0.03369852155447006, -0.00784853845834732, 0.02343153767287731, -0.01835508458316326, -0.012194895185530186, 0.005735251121222973, -0.029135417193174362, -0.009873415343463421, 0.04113638028502464, 0.030184932053089142, -0.01989513263106346, -0.00505078537389636, -0.023226197808980942, 0.02370532415807247, -0.01647280529141426, -0.030937843024730682, -0.028519397601485252, -0.02253032475709915, 0.0376456044614315, -0.0062001170590519905, 0.023203382268548012, -0.009382882155478, 0.02352279983460903, 0.024777652695775032, 0.0007379394373856485, 0.005247569177299738, -0.014111398719251156, 0.012810913845896721, -0.004275057930499315, -0.025279594585299492, -0.041250456124544144, 0.014487854205071926, -0.025325225666165352, 0.008310552686452866, -0.0006495292764157057, 0.0026979350950568914, 0.006884582806378603, 0.0695873349905014, 0.025348041206598282, -0.0529320053756237, 0.0034508472308516502, 0.00804817397147417, -0.007529121357947588, 0.02210823819041252, 0.010050236247479916, -0.00606892816722393, -0.02598687633872032, -0.02010047249495983, 0.01622183434665203, -0.010928633622825146, 0.051198024302721024, 0.04102230444550514, -0.01125945895910263, -0.01884561777114868, 0.06256015598773956, 0.03967618569731712, 0.00277493754401803, 0.04168395325541496, 0.01668955199420452, -0.02450386807322502, -0.01190970093011856, -0.01664392091333866, -0.005966258235275745, 0.02125265635550022, -0.013335670344531536, 0.02429852820932865, 0.0005700314650312066, 0.021800227463245392, -0.02409318834543228, 0.027150467038154602, -0.02338590659201145, -0.03253493085503578, -0.00412960909307003, 0.005498540122061968, 0.024732021614909172, -0.00590921938419342, -0.02400192618370056, -0.00942280888557434, -0.0065879812464118, 0.005678212270140648, -0.014773048460483551, -0.00236710999161005, 0.003234099829569459, 0.01934755966067314, -0.010255576111376286, 0.005629729479551315, -0.014807271771132946, 0.00994186196476221, -0.005244717467576265, 0.03675580024719238, -0.03620822727680206, -0.0073523009195923805, -0.006125967018306255, 0.0322839580476284, 0.057266950607299805, -0.03219269588589668, 0.0024412604980170727, -0.050148509442806244, 0.0312572605907917, -0.004685737192630768, -0.012491496279835701, -0.015332028269767761, -0.02429852820932865, 0.013883243314921856, 0.03385822847485542, 0.008783974684774876, -0.026876680552959442, -0.019393190741539, 0.0023599802516400814, 0.00403834693133831, -0.01652984321117401, 0.005758066661655903, 0.054894138127565384, -0.03185046464204788, 0.011829846538603306, 0.030572794377803802, 0.03260337561368942, 0.00710703432559967, 0.013278631493449211, -0.03823880851268768, 0.015457513742148876, -0.0378737598657608, -0.0004894642042927444, 0.025393672287464142, -0.02397911064326763, -0.012776690535247326, 0.02402474172413349, 0.029021339491009712, 0.0009789284085854888, 0.0374174490571022, 0.02619221620261669, 0.0028818852733820677, 0.019678384065628052, 0.02032862789928913, -0.030618425458669662, -0.023226197808980942, -0.012537127360701561, 0.011037006974220276, 0.00015569808601867408, 0.01666673645377159, 0.0166553296148777, -0.03488492965698242, 0.00916043110191822, -0.00408397801220417, -0.01846916228532791, 0.0005661100731231272, -0.028633475303649902, 0.0008206457132473588, 0.031120367348194122, 0.007209703791886568, 0.01626746542751789, -0.02015751041471958, 0.025051439180970192, 0.0057951416820287704, -0.012594166211783886, 0.01883421093225479, -0.03983589634299278, -0.007175480481237173, -0.009759338572621346, 0.0019165035337209702, -0.011544652283191681, -0.009263101033866405, 0.02020314149558544, -0.01903955079615116, -0.02035144343972206, -0.027287360280752182, -0.001161452499218285, 0.00888664461672306, -0.01719149388372898, 0.00611455924808979, -0.0055013918317854404, -0.012742467224597931, 0.03928832337260246, 0.0408397801220417, 0.00863567367196083, 0.005147751420736313, -0.0205339677631855, -0.00828203372657299, -0.0022844038903713226, -0.0209332387894392, -0.00047912588343024254, -0.00561832170933485, 0.0036362232640385628, -0.010546473786234856, 0.01197814755141735, 0.002759251743555069, -0.05690190568566322, -0.01053506601601839, 0.01062632817775011, -0.00011621654994087294, -0.027812117710709572, -0.0019564307294785976, -0.00990193523466587, 0.02015751041471958, -0.003165653208270669, 0.008019655011594296, 0.01867450214922428, 0.004280761815607548, 0.02249610237777233, -0.009571109898388386, -0.00879538245499134, 0.01911940425634384, 0.0401553139090538, 0.005720991175621748, -0.005335979629307985, 0.02232498489320278, 0.001386042800731957, 0.0008092379430308938, 0.00478270323947072, 0.054711613804101944, -0.0064054569229483604, 0.00854441151022911, -0.02197134494781494, 0.010774629190564156, 0.010341133922338486, -0.01764780469238758, -0.009930454194545746, -0.02343153767287731, -0.03671016916632652, -0.005236161407083273, 0.00034419348230585456, -0.00933725107461214, -0.015115281566977501, 0.015423290431499481, -0.002050544833764434, 0.01963275484740734, 0.02432134374976158, 0.024891730397939682, 0.02111576311290264, 0.03392667695879936, 0.01609634794294834, -0.015195135958492756, -0.0010345411719754338, 0.012377418577671051, 0.012845137156546116, 0.012149264104664326, 0.01643858104944229, -0.014670378528535366, 0.012582758441567421, 0.0072268154472112656, 0.0032312478870153427, 0.02345435321331024, 0.0012876508990302682, 0.04065725579857826, 0.003570628585293889, 0.0015699928626418114, -0.0018038519192487001, -0.0006773357163183391, 0.011784215457737446, -0.006319898646324873, 0.011151084676384926, -0.030002407729625702, 0.011362127959728241, -0.019724015146493912, 0.009890527464449406, -0.00279632699675858, -0.01868590898811817, 0.0009033519309014082, -0.0011215253034606576, 0.006422568578273058, -0.0382159948348999, -0.007882761768996716, 0.00541298184543848, 0.030184932053089142, 0.0019778201822191477, 0.04709123075008392, -0.025735905393958092, -0.024754837155342102, 0.006770505104213953, -0.0013546714326366782, -0.01573129929602146, -0.02148081175982952, -0.029979592189192772, -0.00942851323634386, 0.004931003786623478, 0.01829804666340351, 0.01319877803325653, -0.03385822847485542, -0.026671340689063072, 0.011761399917304516, -0.0028219944797456264, 0.02231357805430889, 0.02407037280499935, 0.006804728414863348, -0.01736260950565338, -0.00203058123588562, 0.0037274854257702827, -0.00433209678158164, 0.02031721919775009, 0.04303006827831268, -0.01771624945104122, 0.0222451314330101, -0.029888330027461052, -0.0074321553111076355, 0.013495379127562046, 0.029591728001832962, 0.01711163856089115, -0.03595725819468498, -0.02237061597406864, 0.00786564964801073, -0.01611916348338127, -0.01934755966067314, 0.030983474105596542, 0.000664501974824816, 0.006502422969788313, -0.04250531271100044, 0.0022487544920295477, 0.013655087910592556, -0.00710703432559967, 0.0197924617677927, -0.028040273115038872, 0.0368470624089241, 0.04029220715165138, 0.0001554307236801833, -0.026625709608197212, 0.03255774453282356, -0.0028975708410143852, 0.00198352406732738, 0.007620383054018021, -0.004246538504958153, -0.0014701749896630645, 0.03910579904913902, 0.01113967690616846, -0.007112738210707903, -0.010118682868778706, 0.04296162351965904, -0.0009960399474948645, 0.01797862909734249, 0.02137814089655876, -0.01718008518218994, -0.04291599243879318, 0.01980387046933174, 0.0014594802632927895, 0.00933725107461214, 0.024960177019238472, -0.004928152076900005, -0.01915362849831581, -0.013860427774488926, -0.055532973259687424, 0.011670137755572796, -0.0520193837583065, -0.005518503487110138, 0.029842698946595192, 0.015240766108036041, -0.01892547309398651, -0.004118201322853565, -0.03908298537135124, -0.0028790333308279514, 0.0035563691053539515, -0.007181184366345406, -0.04433055222034454, -0.0015371955232694745, 0.0338810458779335, -0.0131759624928236, -0.00040996636380441487, 0.020944645628333092, 0.0373033732175827, 0.014852902851998806, 0.028815999627113342, 0.007928392849862576, -0.013871835544705391, 0.10120964050292969, -0.02230216935276985, 0.0021261211950331926, 0.020670859143137932, -0.025256779044866562, -0.011133973486721516, 0.03299124166369438, 0.004583067260682583, 0.03175920248031616, -0.00791698507964611, -0.004226574674248695, 0.04353201016783714, 0.01681503653526306, 0.042322788387537, 0.006548054050654173, 0.010877298191189766, -0.012548535130918026, -0.01184125430881977, 0.01667814515531063, 0.03130289167165756, 0.02029440365731716, 0.046315502375364304, 0.004064014181494713, -0.022952411323785782, 0.007152664940804243, 0.01889124885201454, 0.010386765003204346, -0.012799506075680256, 0.0014174140524119139, 0.0010773203102871776, -0.006656427402049303, -0.02063663676381111, 0.02404755726456642, 0.00927450880408287, -0.01696333847939968, -0.02384221740067005, 0.00981637742370367, -0.0012199173215776682, -0.03880919888615608, 0.03246648237109184, 0.00584077276289463, 0.01595945470035076, 0.0200776569545269, 0.02343153767287731, -0.012651205062866211, 0.005387314595282078, 0.01590241678059101, 0.0026437481865286827, 0.011584579944610596, -0.025439303368330002, 0.01610775664448738, -0.0244126059114933, -0.004169536288827658, 0.03506745398044586, 0.0037103737704455853, -0.02407037280499935, 0.02307789772748947, -0.0358203649520874, -0.012582758441567421, -0.01975823938846588, 0.019393190741539, 0.04001842066645622, -0.0075120097026228905, 0.0027906231116503477, -0.028701921924948692]}, "1": {"file_path": "hr.jhist_department_ix.md", "full_doc_id": "doc-580cfebdd0187e83c6cb75c4aee86c31", "content": "- Consider compressing or parallelizing if workload or data volume changes\n\n---\n\n## Implementation Details\n\n- **Storage Specifications:**\n  - Inherits tablespace and storage parameters from the default or specified settings for the `HR` schema.\n  - `NOLOGGING` reduces redo log usage during index operations.\n\n- **Special Database Features:**\n  - None explicitly used beyond standard index options.\n\n- **Maintenance & Operations:**\n  - Rebuild index periodically if fragmentation occurs.\n  - Monitor for unused indexes to optimize storage and performance.\n  - Consider enabling logging or parallelism for large-scale operations if business needs change.\n\n---\n\n**Summary:**  \nThe `JHIST_DEPARTMENT_IX` index on `HR.JOB_HISTORY (DEPARTMENT_ID)` is a performance optimization object, crucial for efficient department-based queries in HR analytics and reporting. Its configuration (NOLOGGING, NOCOMPRESS, NOPARALLEL) reflects a balance between performance, resource usage, and operational risk, tailored to the workload and business requirements of the HR schema.", "__id__": "chunk-c10297e38e59f5e62d6dc08247db4315", "__created_at__": 1754139616, "__vector__": [-0.007418617140501738, 0.04321061074733734, 0.06612894684076309, 0.021139776334166527, 0.04189758002758026, -0.0005401326343417168, 0.014861107803881168, -0.010170010849833488, 0.0026350116822868586, -0.0025201216340065002, 0.04597990959882736, 0.027907846495509148, -0.002305262256413698, 0.0031960331834852695, 0.052759915590286255, 0.0030587620567530394, -0.030748765915632248, -0.004022645298391581, 0.04130075126886368, 0.010301314294338226, 0.01334515493363142, 0.01659191958606243, -0.014371705241501331, -0.0019904335495084524, 0.017916886135935783, 0.01570860855281353, -0.025616012513637543, 0.015040157362818718, 0.05409681797027588, -0.0721450075507164, 0.02771686017513275, -0.018656957894563675, -0.02793172001838684, 0.01293930970132351, 0.02893439680337906, 0.01011032797396183, 0.03795849159359932, 0.021796291694045067, 0.02996094711124897, 0.04349708929657936, 0.023503229022026062, -0.030510032549500465, -0.01780945621430874, 0.022369250655174255, -0.0208771713078022, 0.019397027790546417, 0.006976961623877287, -0.02217826433479786, 0.006338351871818304, 0.012831879779696465, -0.02559213899075985, 0.038579195737838745, -0.014455261640250683, 0.003533243201673031, 0.01170386839658022, 0.016544172540307045, -0.01745135709643364, 0.03941476345062256, 0.012246984988451004, -0.02669030986726284, 0.03380454331636429, -0.0568661168217659, -0.026714183390140533, 0.009036030620336533, -0.012294731102883816, 0.05452653765678406, -0.012437970377504826, 0.047603290528059006, -0.013404837809503078, -0.008558565750718117, 0.054287802428007126, 0.019038928672671318, -0.009591084904968739, -0.0018621146446093917, 0.01428814884275198, -0.008194498717784882, -0.001721859211102128, 0.00931057333946228, -0.005553518421947956, -0.011602407321333885, -0.03621574491262436, 0.009215080179274082, -0.002276912797242403, -0.0060936505906283855, -0.003995787817984819, -0.026212844997644424, -0.02836143784224987, -0.0065890210680663586, -0.061211053282022476, -0.0007143328548409045, 0.0017845265101641417, 0.02850467897951603, 0.012414097785949707, 0.019659634679555893, -0.03824497014284134, -0.04624251648783684, -0.003942072857171297, -0.003521306673064828, 0.002696187002584338, 0.06407584249973297, 0.008827139623463154, -0.024613335728645325, 0.016484489664435387, 0.007179884240031242, 0.04108589142560959, 0.028624044731259346, -0.030366793274879456, -0.017439421266317368, 0.02850467897951603, -0.004553825594484806, -0.08384291082620621, -0.024028440937399864, -0.02523403987288475, 0.04168272390961647, -0.006785975303500891, -0.05280766263604164, -0.03478334844112396, 0.030724892392754555, -0.026881296187639236, -0.019098613411188126, -0.025759251788258553, -0.03425813466310501, -0.01178145594894886, -0.021629178896546364, -0.028743410483002663, -0.020411642268300056, 0.03645447641611099, -0.030629398301243782, -0.02421942725777626, -0.028098832815885544, 0.019611887633800507, -0.00547294644638896, 0.014240402728319168, -0.06507851928472519, -0.00807513203471899, -0.010742969810962677, -0.020566819235682487, 0.013906177133321762, -0.009477686136960983, -0.04373582452535629, 0.027430381625890732, -0.018358541652560234, 0.03280186653137207, -0.02290639840066433, -0.010886209085583687, 0.028671791777014732, 0.003112476784735918, 0.01919410564005375, 0.03485496714711189, 0.03506982699036598, -0.0019814809784293175, -0.015589241869747639, -0.024255236610770226, -0.033136092126369476, 0.02065037563443184, -0.02726326882839203, 0.03323158621788025, -0.008475009351968765, 0.013906177133321762, -0.03471172973513603, 0.013727127574384212, 0.037791378796100616, 0.018203364685177803, 0.01032518781721592, 0.0007848335662856698, 0.006577084306627512, -0.03908053785562515, -0.009680609218776226, -0.06417133659124374, 0.024613335728645325, -0.0018859879346564412, -0.08771038055419922, -0.002552947262302041, 0.013189978897571564, 0.04428490996360779, 0.05643639713525772, 0.0035153382923454046, -0.041993074119091034, -0.00814078375697136, -0.005625138524919748, -0.01630544103682041, -0.0335896834731102, -0.04552631825208664, 0.05252118036150932, -0.059301190078258514, -0.04077553749084473, -0.06369387358427048, 0.03461623564362526, -0.009984993375837803, 0.06230922043323517, 0.011244308203458786, 0.008779393509030342, 0.012509590946137905, 0.016484489664435387, -0.002396279014647007, -0.01334515493363142, 0.00978207029402256, -0.00747233210131526, -0.036406729370355606, 0.01860921084880829, 0.02857629768550396, 0.008051258511841297, 0.039748989045619965, 0.015804100781679153, -0.020996537059545517, 0.05075456202030182, -0.013213852420449257, 0.00669048260897398, -0.03979673236608505, -0.05323737859725952, -0.011876949109137058, -0.007478300482034683, 0.043616458773612976, 0.041348498314619064, 0.033136092126369476, -0.03490271419286728, -0.04595603793859482, 0.005353579763323069, -0.021211396902799606, -0.024708827957510948, -0.02297801896929741, 0.007818493992090225, -0.010522142052650452, 0.016639666631817818, 0.0007766271592117846, 0.032682500779628754, 0.0031661917455494404, -0.055958934128284454, 0.007090359460562468, 0.012097776867449284, 0.01766621693968773, -0.045788925141096115, -0.04001159220933914, 0.005443104542791843, -0.042804766446352005, -0.030629398301243782, -0.041778214275836945, -0.03010418638586998, 0.04306737333536148, 0.03471172973513603, -0.02907763607800007, 0.018871815875172615, -0.025066927075386047, -0.034353628754615784, 0.026523197069764137, 0.024195553734898567, -0.03428201004862785, -0.09172108769416809, 0.05705710127949715, -0.0015681750373914838, -0.034950461238622665, -0.032754119485616684, -0.010951860807836056, -0.023610658943653107, -0.07018739730119705, -0.03452074155211449, -0.03105911798775196, 0.030414540320634842, -0.017690090462565422, 0.026594817638397217, 0.014849171042442322, -0.01746329292654991, 0.027955593541264534, 0.015839911997318268, -0.028194325044751167, 0.0487014576792717, 0.057916540652513504, -0.03955800086259842, -0.05147075653076172, -0.03934314101934433, 0.01906280219554901, 0.03621574491262436, 0.014705930836498737, -0.023980693891644478, 0.0005434898193925619, 0.02611735090613365, -0.022094707936048508, 0.02435072883963585, -0.023682277649641037, -0.012879625894129276, -0.01576829142868519, -0.009811912663280964, 0.007048581261187792, 0.03158432990312576, 0.04894019290804863, 0.030223554000258446, -0.009698513895273209, 0.0215933695435524, -0.00492684543132782, 0.014061353169381618, -0.025830872356891632, -0.025783125311136246, 0.02349129132926464, 0.005171546246856451, -0.012426034547388554, 0.030581653118133545, -0.005607233382761478, -0.011130910366773605, 0.01920604147017002, -0.042661525309085846, 0.03528468683362007, 0.02516242116689682, 0.03786299750208855, -0.028456931933760643, 0.007681223098188639, 0.02356291189789772, -0.011882917024195194, -0.025783125311136246, -0.03158432990312576, 0.026165097951889038, -0.022667666897177696, 0.0044911582954227924, 0.029220877215266228, -0.01011032797396183, -0.026881296187639236, -0.020912980660796165, 0.03294510766863823, 0.01570860855281353, -0.007281345780938864, -0.0069888983853161335, 0.004610524512827396, -0.03652609512209892, 0.017057448625564575, -0.02494756132364273, 0.0039241681806743145, -0.03230052813887596, 0.02611735090613365, -0.026356084272265434, -0.013882303610444069, 0.010426648892462254, 0.0025544394738972187, 0.002169483108446002, -0.020411642268300056, 0.024028440937399864, 0.009280731901526451, -0.027502000331878662, -0.03003256767988205, -0.012079872190952301, -0.0053714849054813385, -0.02182016521692276, -0.022058898583054543, 0.0028110770508646965, -0.05529048293828964, -0.01396586000919342, -0.037934619933366776, 0.016162199899554253, 0.006839690264314413, 0.03986835479736328, 0.006433844566345215, -0.0171529408544302, -0.03249151259660721, 0.005807172041386366, -0.01304673869162798, 0.0036048630718141794, 0.007585729938000441, 0.0020008780993521214, 0.006809848826378584, -0.08026191592216492, -0.05562470853328705, 0.020698120817542076, -0.022214073687791824, -0.036120250821113586, 0.060112882405519485, -0.03031904622912407, 0.05347611382603645, -0.007209726143628359, 0.006684514228254557, 0.05237794294953346, 0.06092457100749016, 0.015505685470998287, 0.03098749741911888, -0.008809234946966171, -0.0024291048757731915, -0.028695665299892426, -0.04364033043384552, 0.01897924579679966, 0.01877632364630699, 0.003774960059672594, 0.022667666897177696, 0.023741960525512695, 0.021653052419424057, 0.021497875452041626, 0.007191821001470089, -0.009549306705594063, 0.019086675718426704, 0.0228347796946764, -0.0021575463470071554, 0.013751000165939331, -0.03024742752313614, -0.03557116538286209, 0.002855839440599084, -0.017427483573555946, -0.030653271824121475, -0.0017964631551876664, -0.05424005910754204, 0.034067150205373764, -0.002669329522177577, 0.03795849159359932, 0.03848370537161827, 0.015732482075691223, 0.0016770968213677406, -0.038006238639354706, 0.0003750713658519089, -0.020638437941670418, -0.017618469893932343, -0.053619351238012314, -0.01490885391831398, 0.05519498884677887, 0.014598501846194267, -0.04115751013159752, 0.012700576335191727, 0.011608375236392021, 0.015171459876000881, 0.008839076384902, 0.03067714534699917, -0.06517401337623596, -0.04122912883758545, 0.04180208966135979, -0.014407515525817871, 0.01174564566463232, -0.024195553734898567, 0.011441262438893318, 0.0098178805783391, -0.036263491958379745, -0.04569343104958534, 0.026809675619006157, 0.016484489664435387, -0.03721842169761658, 0.005278975702822208, -0.023825516924262047, -0.026141224429011345, 0.04994286969304085, 0.03244376927614212, 0.02399262972176075, -0.06302542239427567, 0.017678152769804, 0.045287586748600006, 0.0033810511231422424, 0.05476526916027069, -0.004556809552013874, -0.002336595905944705, 0.00854662898927927, 0.0035780055914074183, 0.033780671656131744, -0.021951468661427498, 0.02160530537366867, 0.0047567482106387615, 0.011966473422944546, 0.0007639444665983319, -0.005243165884166956, 0.008856981061398983, 0.03948638215661049, 0.033923909068107605, -0.007699127774685621, 0.02661868929862976, -0.03354193642735481, 0.006553211249411106, -0.0018531621899455786, 0.002700663171708584, 0.0023410720750689507, 0.011590470559895039, 0.000630776456091553, 0.009686577133834362, 0.039390888065099716, 0.026069605723023415, -0.012127618305385113, -0.0010489316191524267, 0.004613508470356464, -0.007526046596467495, -0.04488173872232437, 0.00665467232465744, -0.033637430518865585, 0.07262247055768967, -0.011721773073077202, 0.033852290362119675, 0.021927595138549805, -0.04442814737558365, 0.0077050961554050446, 0.013691317290067673, -0.053858086466789246, 0.05743907392024994, -0.03325545787811279, -0.00763347651809454, -0.009280731901526451, 0.04951315000653267, 0.050133854150772095, 0.0774926170706749, -0.005577391944825649, 0.02444622293114662, 0.012318604625761509, -0.015983151271939278, -0.00040360738057643175, 0.040393564850091934, -0.011047353968024254, -0.0018695751205086708, 0.022130517289042473, -0.03504595533013344, -0.06631992757320404, 0.06741809844970703, 0.018370477482676506, 0.010563920252025127, 0.010772811248898506, -0.004279282875359058, 0.029268622398376465, 0.010623603127896786, 0.024637209251523018, -0.02719164825975895, -0.03237214684486389, -0.00012953110854141414, -0.02131882682442665, 0.02146206609904766, 0.05070681497454643, 0.019886430352926254, 0.021115902811288834, -0.012235048227012157, -0.031393345445394516, -0.009083777666091919, 0.030342919752001762, 0.005469962023198605, -0.015446002595126629, -0.01680677942931652, -0.001985957147553563, -0.008158688433468342, 0.016377059742808342, 0.006815817207098007, 0.03273024782538414, -0.04588441923260689, -0.10284602642059326, 0.015469876118004322, 0.001096678082831204, -0.029149256646633148, -0.0006557687884196639, 0.03003256767988205, 0.04242279380559921, -0.02466108277440071, -0.024613335728645325, -0.0009549306123517454, 0.008463072590529919, -0.012079872190952301, 0.009101682342588902, -0.0023977712262421846, 0.009656735695898533, -0.01606670767068863, 0.031035244464874268, 0.030510032549500465, -0.0014003162505105138, 0.01993417739868164, 0.02182016521692276, 0.02153368666768074, 0.019456710666418076, -0.01578022912144661, -0.03774363175034523, 0.02256023697555065, 0.015541495755314827, -0.012306667864322662, -0.0016770968213677406, -0.03387616202235222, 0.020817488431930542, -0.02371808886528015, 0.002669329522177577, 0.005237197503447533, -0.003894326277077198, -0.036120250821113586, 0.03292123228311539, -0.010557951405644417, -0.03922377526760101, 0.01745135709643364, -0.03707518056035042, -0.059014711529016495, 0.014001669362187386, 0.04679160192608833, -0.005198403727263212, -0.014538818039000034, -0.015338572673499584, 0.02640383131802082, -0.005177514627575874, -0.01490885391831398, -0.004231536295264959, 0.03948638215661049, 0.06340739130973816, -0.008236276917159557, -0.03542792424559593, 0.012987055815756321, 0.030605526641011238, -0.034067150205373764, -0.006529337726533413, 0.038006238639354706, 0.03709905594587326, -0.027000661939382553, -0.02326449751853943, 0.007299250923097134, 0.006475623231381178, 0.038435958325862885, -0.019671570509672165, -0.015827974304556847, 0.001977004809305072, 0.014491071924567223, 0.007669286336749792, -0.0028677762020379305, 0.018967309966683388, 0.009400098584592342, -0.0009318033698946238, 0.011423357762396336, -0.026356084272265434, -0.029769960790872574, 0.00030550319934263825, 0.015601178631186485, 0.007818493992090225, 0.044117797166109085, -0.03220503404736519, -0.035762153565883636, -0.02466108277440071, -0.01716487854719162, -0.02800333872437477, -0.04936991259455681, 0.05505174770951271, 0.00902409479022026, -0.010933956131339073, 0.01811980828642845, -0.04595603793859482, 0.010337124578654766, 0.013643571175634861, -0.06522176414728165, -0.012891562655568123, 0.014932727441191673, 0.02146206609904766, -0.04791364073753357, -0.025401152670383453, -0.005195419304072857, 0.027812354266643524, -0.01240216102451086, -0.047078076750040054, 0.02340773679316044, -0.01290349941700697, 0.009071840904653072, 0.01665160246193409, 0.004694080911576748, -0.012843816541135311, 0.04882082715630531, -0.0003830912755802274, 0.030557779595255852, 0.040321946144104004, 0.028098832815885544, 0.017343927174806595, 0.037337787449359894, -0.006953088566660881, 0.004986528307199478, -0.014956600964069366, -0.03129785135388374, -0.001329442486166954, -0.01759459637105465, -0.01943283900618553, 0.04244666546583176, 0.07281345874071121, 0.0034795282408595085, 0.002814061241224408, -0.017260370776057243, -0.020304212346673012, -0.02124720625579357, 0.0319901742041111, -0.005329706706106663, 0.017713962122797966, -0.012121650390326977, -0.017343927174806595, 0.03382841870188713, 0.03010418638586998, -0.008624217472970486, 0.02726326882839203, 0.05724808946251869, 0.025759251788258553, -0.005517708603292704, -0.01076087448745966, 0.0710945874452591, 0.010850399732589722, -0.023610658943653107, -0.014789487235248089, -0.017761709168553352, -0.025568265467882156, -0.02057875506579876, 0.0346401073038578, -0.0029379036277532578, -0.025210168212652206, 0.02226182073354721, -0.04216018691658974, -0.007102296222001314, -0.026212844997644424, 0.010229694657027721, 0.025783125311136246, 0.030748765915632248, -0.004282266832888126, 0.0519004762172699, -0.00019881952903233469, 0.018931498751044273, -0.02719164825975895, 0.01348839420825243, -0.006899373605847359, 0.018060125410556793, -0.015553432516753674, -0.020316150039434433, -0.03428201004862785, 0.003378066932782531, 0.03578602522611618, -0.013082548975944519, 0.003545179730281234, -0.008116910234093666, -0.004622461274266243, -0.010772811248898506, -0.015362446196377277, 0.028265945613384247, -0.0002001250977627933, -0.012593147344887257, 0.02456558868288994, -0.030223554000258446, -0.03521306812763214, 0.014849171042442322, -0.00418378971517086, -0.030295172706246376, -0.021485939621925354, 0.017331991344690323, -0.029913201928138733, 0.024326857179403305, -0.02080555073916912, -0.026236718520522118, -0.014216529205441475, 0.03798236697912216, 0.020196782425045967, -0.021426256746053696, 0.0021262126974761486, -0.04421328753232956, -0.010265504010021687, 0.014180718921124935, 0.022739285603165627, 0.0074902367778122425, 0.0013674905057996511, 0.018072061240673065, 0.013762936927378178, -0.02857629768550396, 0.018203364685177803, -0.03070101886987686, -0.008898759260773659, -0.008003512397408485, -0.024100059643387794, 0.01552955899387598, -0.018668893724679947, -0.01586378552019596, -0.047746527940034866, 0.014825297519564629, 0.0016905255615711212, 0.0478181466460228, 0.034353628754615784, -0.023670341819524765, 0.008361611515283585, -0.014562691561877728, -0.03817335143685341, 0.030199680477380753, -0.017355864867568016, -0.0028394265100359917, 0.013715190812945366, -0.009549306705594063, 0.02814657986164093, -0.03287348523736, 0.02604573220014572, -0.03132172301411629, 0.030892005190253258, -0.02960284799337387, 0.014550754800438881, -0.026570944115519524, -0.0012346954317763448, -0.016568046063184738, -0.03134559839963913, 0.04502497985959053, 0.028910523280501366, -0.01414490956813097, -0.013894240371882915, 0.03812560439109802, -0.0035541323013603687, 0.027167774736881256, 0.001868083025328815, 0.013691317290067673, -0.0034795282408595085, -0.010802652686834335, -0.03191855549812317, 0.004282266832888126, -0.02754974737763405, -0.010396807454526424, -0.009555274620652199, -0.007842367514967918, -0.030653271824121475, -0.003951025195419788, -0.032777994871139526, 0.002739457180723548, -0.005299864802509546, 0.015207270160317421, 0.0070366449654102325, -0.00814078375697136, -0.024088123813271523, 0.0035660688299685717, -0.07591698318719864, 0.023037701845169067, 0.04884469881653786, -0.04877308011054993, -0.011309959925711155, 0.027096156030893326, 0.010086454451084137, 0.012736386619508266, 0.02757362090051174, -0.013213852420449257, -0.008176593109965324, -0.04118138179183006, -0.0048731304705142975, -0.009143460541963577, -0.0009534385171718895, -0.005225261207669973, -0.014455261640250683, 0.0053983423858881, -0.0019038928439840674, -0.020316150039434433, 0.009501559659838676, -0.013989733532071114, -0.005093958228826523, -0.02196340449154377, 0.017176814377307892, -0.007072454784065485, 0.0006248081335797906, 0.018310794606804848, 0.02552052028477192, -0.035356305539608, -0.006066793110221624, 0.021366573870182037, -0.050945546478033066, -0.01320191565901041, -0.024243300780653954, 0.01942090131342411, 0.013798747211694717, -0.022679602727293968, 0.022166326642036438, -0.005347611382603645, -0.03993997350335121, -0.022058898583054543, -0.006096635013818741, 0.00042524252785369754, 0.024410413578152657, -0.038794055581092834, 0.02726326882839203, 0.02356291189789772, -0.031082991510629654, 0.04275701940059662, -0.004031597636640072, 0.033040598034858704, 0.005299864802509546, 0.02400456741452217, 0.007878177799284458, 0.0028498710598796606, -0.003959977999329567, -0.02224988304078579, -0.004386712331324816, -0.008087068796157837, 0.008469040505588055, -0.0013152677565813065, 0.041133638471364975, -0.028671791777014732, -0.004225567914545536, 0.008922632783651352, -0.02690516971051693, 0.021139776334166527, 0.006636767648160458, 0.010086454451084137, 0.04056067764759064, 0.019528331235051155, -0.028170453384518623, -0.009286700747907162, 0.04483399540185928, 0.025616012513637543, -0.03652609512209892, -0.02640383131802082, -0.018800197169184685, -0.013392901048064232, 0.060972318053245544, -0.030868131667375565, 0.019468648359179497, 0.020710058510303497, -0.007728969678282738, 0.003649625461548567, 0.012235048227012157, -0.00232764333486557, -0.0007997543434612453, -0.028337566182017326, 0.014574628323316574, 0.018298858776688576, 0.013810683973133564, -0.012127618305385113, 0.03187080845236778, -0.030342919752001762, -0.017845265567302704, -0.010975734330713749, 0.01877632364630699, -0.014646247960627079, 0.022500554099678993, 0.0040942649357020855, 0.02618897147476673, 0.013798747211694717, -0.004691096488386393, -0.0008489929605275393, -0.0008542152354493737, -0.0010422172490507364, -7.203944551292807e-05, 0.026785802096128464, -0.0018069077050313354, 0.05280766263604164, 0.0019262740388512611, -0.0021277046762406826, -0.01992223970592022, -0.031894683837890625, 0.006189143750816584, 0.04574117809534073, -0.026809675619006157, -0.03962961956858635, -0.018143681809306145, -0.01599508710205555, -0.03320771083235741, 0.00970448274165392, -0.029937073588371277, 0.001935226609930396, 0.009322510100901127, 0.005816124379634857, 0.00034411074011586607, 0.04466687887907028, -0.013094485737383366, 0.04182596132159233, -0.030199680477380753, 0.029769960790872574, -0.025974111631512642, -0.035380180925130844, 0.006135428790003061, -0.011327864602208138, 0.00410918565467, -0.00407039187848568, 0.01868082955479622, 0.03795849159359932, -0.012121650390326977, 0.00747233210131526, -0.003694387851282954, 0.023968758061528206, 0.0011130910133942962, -0.013225788250565529, -0.03170369565486908, 0.01523114275187254, -0.00636222492903471, 0.026308337226510048, 0.03803011402487755, 0.014025542885065079, -0.03609637916088104, 0.04137236997485161, -0.03315996378660202, 0.008952474221587181, 0.00043382198782637715, 0.029578974470496178, -0.014431389048695564, 0.0024007551837712526, 0.013834556564688683, -0.012796069495379925, 0.023383863270282745, 0.003807785687968135, -0.01687839813530445, 0.0008079608087427914, 0.008851013146340847, 0.007352965418249369, 0.007508141919970512, 0.0057086949236691, -0.012205206789076328, 0.03721842169761658, 0.03039066679775715, 0.05643639713525772, 0.018203364685177803, 0.031082991510629654, 0.014825297519564629, 0.027143901214003563, -0.04044131189584732, 0.007639444898813963, 0.03077263943850994, -0.0008691360708326101, 0.025639886036515236, 0.07730163633823395, -0.009859658777713776, -0.015338572673499584, 0.010313251055777073, 0.030366793274879456, 0.016926145181059837, 0.019038928672671318, 0.021271079778671265, -0.016973892226815224, -0.03165594860911369, 0.022942209616303444, 0.002239610766991973, -0.041276875883340836, -0.01222311146557331, 0.026021858677268028, -0.025974111631512642, 0.016711285337805748, 0.014001669362187386, 0.01058182492852211, 0.058728232979774475, 0.022942209616303444, -0.008463072590529919, 0.022130517289042473, 0.0021485937759280205, 0.041348498314619064, -0.021283017471432686, -0.0023246591445058584, 0.0050909738056361675, -0.009209112264215946, 0.012796069495379925, 0.0009429939673282206, -0.010414712131023407, -0.020483262836933136, 0.008421294391155243, -0.02466108277440071, 0.021855974569916725, -0.01094589289277792, -0.012449907138943672, -0.0335896834731102, -0.025711506605148315, -0.0008915172074921429, -0.004279282875359058, 0.004103217273950577, -0.019540268927812576, 0.0019262740388512611, -0.03261088207364082, 0.021271079778671265, 0.03533243387937546, -0.013739064335823059, -0.00887488666921854, 0.01854952797293663, -0.002802124712616205, 0.0009049459476955235, -0.031154610216617584, -0.010384870693087578, 0.023515164852142334, -0.02014903724193573, -0.026809675619006157, -0.013798747211694717, -0.024195553734898567, -0.00985369086265564, 0.0043091243132948875, 0.029769960790872574, 0.031226230785250664, 0.007806557696312666, -0.025854745879769325, 0.008928601630032063, 0.02413587085902691, -0.03163207694888115, -0.01862114667892456, 0.005607233382761478, 0.03478334844112396, 0.01549374870955944, -0.007740906439721584, -0.0033213680144399405, -0.005270023364573717, 0.005687805823981762, 0.029722215607762337, -0.01320191565901041, -0.017618469893932343, -0.027311014011502266, -0.015410192310810089, 0.0004032343567814678, 0.007215694524347782, -0.022058898583054543, 0.011841138824820518, 0.007806557696312666, 0.009662704542279243, -0.006177206989377737, -0.05099329352378845, 0.009871595539152622, 0.014455261640250683, 0.03657384216785431, 0.018871815875172615, -0.007496205158531666, -0.009083777666091919, -0.007394743617624044, 0.014682058244943619, 0.015171459876000881, 0.004255409352481365, -0.02938799001276493, 0.023037701845169067, -0.025401152670383453, 0.023395800963044167, 0.02501918189227581, 0.021617243066430092, 0.0050402432680130005, 0.02509080059826374, 0.006780007388442755, -0.012270857580006123, -0.027072282508015633, -0.01490885391831398, 0.014276212081313133, 0.008242244832217693, -0.002967745065689087, 0.00538043724372983, -0.0020396721083670855, 0.003551148111000657, -0.022226011380553246, 0.00966867245733738, 0.00851081870496273, -0.013619697652757168, -0.041205257177352905, -0.02924474887549877, 0.03077263943850994, 0.016639666631817818, 0.03848370537161827, -0.011256244964897633, 0.040321946144104004, -0.021294953301548958, 0.007693159859627485, 0.007639444898813963, -0.005971300415694714, 0.008415326476097107, -0.02116364985704422, -0.014097162522375584, 0.03332707658410072, 0.016997765749692917, -0.02516242116689682, 0.0013324266765266657, -0.027072282508015633, 0.037122927606105804, -0.019253788515925407, -0.029841581359505653, -0.007263440638780594, -0.034449122846126556, 0.039892226457595825, -0.011071227490901947, 0.011327864602208138, -0.013810683973133564, 0.009089745581150055, 0.011668059043586254, -0.008289990946650505, 0.019086675718426704, -0.006224953569471836, 0.008463072590529919, -0.005368500482290983, -0.020817488431930542, -0.024243300780653954, -0.005675869062542915, 0.0017293195705860853, -0.0031632075551897287, 0.003013999667018652, -0.002218721667304635, 0.01759459637105465, 0.0456695593893528, 0.005231229588389397, -0.04576504975557327, -0.011017512530088425, 0.0035093699116259813, 0.003357177833095193, 0.02458946220576763, 4.7839785111136734e-05, -0.0019158294890075922, -0.007150042802095413, -0.01563698798418045, 0.014264275319874287, -0.022655729204416275, 0.0199938602745533, 0.04354483634233475, -0.019074739888310432, -0.02669030986726284, 0.061211053282022476, 0.03528468683362007, -0.006893405225127935, 0.03432975709438324, -0.0024485017638653517, -0.009537369944155216, -0.000494251202326268, -0.01592346839606762, -0.006887436844408512, 0.01635318621993065, 0.0022858651354908943, 0.004885067231953144, -0.0037212450988590717, 0.02917313016951084, -0.014634311199188232, 0.02886277809739113, 0.0021485937759280205, -0.01396586000919342, -0.004935797769576311, 0.024470096454024315, 0.03456848859786987, 0.01058779377490282, -0.027430381625890732, 0.0001039792550727725, -0.005651995539665222, -0.0031840966548770666, 0.0009213588200509548, -0.00013018389290664345, 0.01087427232414484, 0.017188750207424164, -0.005108878947794437, 0.011644185520708561, -0.009316542185842991, 0.013619697652757168, -0.017045510932803154, 0.03468785434961319, -0.036048632115125656, 0.0004050994466524571, 0.01304673869162798, 0.05213921144604683, 0.04734068363904953, -0.014419452287256718, -0.003706324379891157, -0.035595037043094635, -0.006469654850661755, 0.0122171426191926, -0.018454033881425858, -0.01356001477688551, -0.043306104838848114, -4.4715747208101675e-05, 0.041563354432582855, 0.011912758462131023, -0.02349129132926464, -0.01796463318169117, 0.030151933431625366, 0.010498268529772758, -0.003551148111000657, 0.01120253000408411, 0.046934835612773895, -0.037266168743371964, 0.01236635074019432, 0.03905666247010231, 0.026141224429011345, 0.004882082808762789, 0.017057448625564575, -0.029793834313750267, 0.02080555073916912, -0.035236939787864685, 0.00792592391371727, 0.024613335728645325, -0.019038928672671318, 0.008343705907464027, 0.025687633082270622, 0.017224561423063278, -0.015016283839941025, 0.032777994871139526, 0.03993997350335121, -0.01650836318731308, 0.015064029954373837, 0.032396022230386734, -0.02276315912604332, -0.037266168743371964, -0.013333218172192574, -0.0048731304705142975, 0.013977796770632267, 0.013548078015446663, 0.01599508710205555, -0.02029227651655674, -0.0035690530203282833, 0.012927372939884663, -0.011113005690276623, -0.008713741786777973, -0.045001108199357986, -0.009626894257962704, 0.02320481464266777, 0.00305428565479815, 0.014861107803881168, -0.025926364585757256, 0.024159744381904602, -0.0025111690629273653, -0.005461009684950113, 0.014168783091008663, -0.034449122846126556, -0.0006296574138104916, -0.00046515563735738397, -0.015756355598568916, 0.00271856808103621, 0.006529337726533413, 0.009585116058588028, -0.01135173812508583, -0.02444622293114662, -0.007299250923097134, 0.0030229520052671432, 0.01840628869831562, -0.010319218970835209, 0.015159523114562035, -0.0029110463801771402, 0.008057227358222008, 0.03449686989188194, 0.041348498314619064, -0.0006490544183179736, 0.00916136521846056, -0.02900601737201214, -0.02160530537366867, 0.006923246663063765, -0.026379957795143127, -0.00901812594383955, -0.0021351652685552835, 0.006959056481719017, -0.009030062705278397, 0.0018665909301489592, 0.02974608913064003, -0.037051308900117874, -0.02347935549914837, 0.03077263943850994, 0.002033703727647662, -0.012258920818567276, 0.0005949665210209787, -0.005428183823823929, -0.0030095234978944063, -0.011751614511013031, 0.011477072723209858, 0.028552424162626266, 0.007299250923097134, 0.017487166449427605, -0.006013078615069389, -0.00890472810715437, 0.03387616202235222, 0.025281786918640137, 0.00514468876644969, -0.027478128671646118, 0.015983151271939278, 0.004577698651701212, 0.01094589289277792, 0.005881775636225939, 0.043974556028842926, -0.012557337060570717, 0.023145131766796112, -0.01538631971925497, -0.002648440422490239, 0.02137850970029831, -0.0035750214010477066, 0.0047090016305446625, -0.008946506306529045, -0.032777994871139526, -0.01622188463807106, 0.020029669627547264, 0.014896917156875134, -0.03241989389061928, 0.0011459167581051588, 0.0048283678479492664, 0.004691096488386393, 0.004180805757641792, 0.024828195571899414, 0.020745867863297462, 0.04843885451555252, 0.00814078375697136, -0.02219020016491413, 0.032252781093120575, 0.0072037577629089355, 0.019444774836301804, 0.012879625894129276, 0.0005334182642400265, -0.023586785420775414, 0.014252339489758015, 9.45954798226012e-06, -0.012831879779696465, 0.008480977267026901, -0.0006968009402044117, 0.025186294689774513, -0.001379427150823176, -0.010856367647647858, -0.004553825594484806, 0.0050879898481070995, 0.010922019369900227, -0.002864792011678219, 0.022882524877786636, -0.01745135709643364, 0.02466108277440071, -0.017188750207424164, 0.004228552337735891, -0.013798747211694717, -0.019158296287059784, 0.0024977403227239847, -0.0017352879513055086, 0.008457104675471783, -0.04232729971408844, -0.0028274899814277887, -0.017916886135935783, 0.029650595039129257, 0.002455962123349309, 0.0522347018122673, -0.027740733698010445, -0.02516242116689682, 0.019647696986794472, -0.013118359260261059, -0.029101509600877762, -0.03344644606113434, -0.0032945105340331793, -0.00985369086265564, 0.003795849159359932, 0.017785582691431046, 0.006630799267441034, -0.054001323878765106, -0.025329533964395523, 0.026952916756272316, 0.0043777599930763245, 0.05801203474402428, 0.005093958228826523, 0.004124106373637915, -0.009465749375522137, -0.015887657180428505, 0.002230658195912838, -0.009429940022528172, 0.032252781093120575, 0.02917313016951084, -0.005610217340290546, 0.015290826559066772, -0.030342919752001762, 0.03191855549812317, 0.010086454451084137, 0.03390003740787506, 0.02886277809739113, -0.03514144569635391, -0.020328085869550705, 0.012987055815756321, -0.027907846495509148, -0.03156045824289322, 0.02712002955377102, 0.015302763320505619, -0.0048731304705142975, -0.03631123527884483, -0.010838462971150875, 0.009238953702151775, 0.0023530088365077972, 0.02530566044151783, -0.012121650390326977, 0.035666659474372864, 0.03265862539410591, -0.01076087448745966, -0.012593147344887257, 0.02473270148038864, -0.010969765484333038, -0.002530566183850169, -0.008421294391155243, -0.023288371041417122, 0.009221049025654793, 0.020471325144171715, 0.00869583711028099, 0.005428183823823929, 0.013333218172192574, 0.039892226457595825, 0.005177514627575874, 0.022930271923542023, 0.015410192310810089, -0.013548078015446663, -0.032037921249866486, 0.019504457712173462, -0.013189978897571564, 0.0008176593109965324, 0.04211243987083435, -0.006684514228254557, -0.011853075586259365, -0.021641114726662636, -0.061115559190511703, 0.011506914161145687, -0.04908343032002449, 0.008421294391155243, 0.018573401495814323, 0.009298636578023434, 0.0023246591445058584, -0.013464521616697311, -0.026379957795143127, -0.0010765350889414549, 0.009925310499966145, 0.01642480678856373, -0.02384939044713974, 0.006230921950191259, 0.018931498751044273, -0.005264054983854294, 0.007191821001470089, 0.03067714534699917, 0.03748102858662605, 0.02458946220576763, 0.02473270148038864, -0.0060906666330993176, 0.01644868031144142, 0.11029448360204697, -0.009364288300275803, 0.02349129132926464, 0.02406425029039383, -0.011566597037017345, -0.01170386839658022, 0.04827174171805382, 0.009065872989594936, 0.030629398301243782, -0.011489009484648705, -0.018597273156046867, 0.054956257343292236, 0.01897924579679966, 0.06655866652727127, 0.026451576501131058, 0.010904114693403244, -0.036836449056863785, -0.000518497487064451, -0.0007106026750989258, 0.017570722848176956, 0.02190372161567211, 0.055958934128284454, -0.0035004173405468464, -0.03256313502788544, 0.008642122149467468, 0.012258920818567276, 0.014121036045253277, 0.0032139383256435394, 0.004535920452326536, -0.008880854584276676, -0.012426034547388554, -0.03323158621788025, 0.029101509600877762, 0.016412869095802307, -0.01709325797855854, -0.027096156030893326, 0.003870453219860792, -0.0002842410758603364, -0.033709049224853516, 0.01192469522356987, 0.012246984988451004, -0.013655507005751133, 0.014455261640250683, 0.02167692594230175, -0.014001669362187386, -0.011865012347698212, 0.03249151259660721, 0.011095100082457066, 0.007728969678282738, -0.034425247460603714, 0.0004916400648653507, -0.020459389314055443, -8.40227075968869e-05, 0.02304963767528534, -0.014276212081313133, -0.03337482362985611, -0.008457104675471783, -0.038077857345342636, -0.00011955283844145015, -0.009447844699025154, 0.013452584855258465, 0.026523197069764137, -0.005073069129139185, -0.008970379829406738, -0.023312244564294815]}}